{"cameraMode":{"drawMode":0,"name":"Shaded","section":"Shading Mode"},"sceneLighting":true,"audioPlay":false,"sceneViewState":{"showFog":true,"showMaterialUpdate":false,"showSkybox":true,"showFlares":true,"showImageEffects":true,"showParticleSystems":true},"in2DMode":false,"pivot":{"x":0.0000014942437474019244,"y":-25.778078079223634,"z":17.267337799072267},"rotation":{"x":-0.6734738945960999,"y":-1.7370385685389068e-10,"z":-4.063443331814298e-11,"w":-0.7392110228538513},"size":44.31948471069336,"orthographic":false}